setup.py
dsnd_probability_7769/Binomialdistribution.py
dsnd_probability_7769/Gaussiandistribution.py
dsnd_probability_7769/Generaldistribution.py
dsnd_probability_7769/__init__.py
dsnd_probability_7769.egg-info/PKG-INFO
dsnd_probability_7769.egg-info/SOURCES.txt
dsnd_probability_7769.egg-info/dependency_links.txt
dsnd_probability_7769.egg-info/not-zip-safe
dsnd_probability_7769.egg-info/top_level.txt