Metadata-Version: 1.0
Name: dsnd-probability-7769
Version: 0.1
Summary: Gaussian and Binomial distributions
Home-page: UNKNOWN
Author: Maaz
Author-email: UNKNOWN
License: UNKNOWN
Platform: UNKNOWN
